helloworld.py
helloworld_message-0.0.1.dist-info/METADATA
helloworld_message-0.0.1.dist-info/WHEEL
helloworld_message-0.0.1.dist-info/top_level.txt
helloworld_message-0.0.1.dist-info/RECORD
