Metadata-Version: 2.1
Name: helloworld-message
Version: 0.0.1
Summary: Just Says Hello
Home-page: UNKNOWN
Author: UNKNOWN
Author-email: UNKNOWN
License: UNKNOWN
Platform: UNKNOWN
